aws_pylambda_sam_builder/__init__.py
aws_pylambda_sam_builder/__main__.py
aws_pylambda_sam_builder-0.2.4.dist-info/METADATA
aws_pylambda_sam_builder-0.2.4.dist-info/WHEEL
aws_pylambda_sam_builder-0.2.4.dist-info/entry_points.txt
aws_pylambda_sam_builder-0.2.4.dist-info/RECORD
