Metadata-Version: 2.3
Name: aws_pylambda_sam_builder
Version: 0.2.4
Summary: A tool for building AWS Lambda functions from Python projects.
License: MIT
Author: Alex Loiko
Author-email: alexandreloiko@gmail.com
Requires-Python: >=3.11
Classifier: License :: OSI Approved :: MIT License
Classifier: Programming Language :: Python :: 3
Classifier: Programming Language :: Python :: 3.11
Classifier: Programming Language :: Python :: 3.12
Classifier: Programming Language :: Python :: 3.13
Requires-Dist: filelock (>=3.18.0,<4.0.0)
Project-URL: Homepage, https://github.com/aleloi/aws_pylambda_sam_builder
